nonebot_plugin_treehelp/__init__.py
nonebot_plugin_treehelp/config.py
nonebot_plugin_treehelp/data_source.py
nonebot_plugin_treehelp-0.4.1.dist-info/LICENSE
nonebot_plugin_treehelp-0.4.1.dist-info/METADATA
nonebot_plugin_treehelp-0.4.1.dist-info/WHEEL
nonebot_plugin_treehelp-0.4.1.dist-info/RECORD
