Metadata-Version: 2.1
Name: nonebot-plugin-treehelp
Version: 0.4.1
Summary: 适用于 Nonebot2 的树形帮助插件
Home-page: https://github.com/he0119/nonebot-plugin-treehelp
License: MIT
Author: hemengyang
Author-email: hmy0119@gmail.com
Requires-Python: >=3.8,<4.0
Classifier: License :: OSI Approved :: MIT License
Classifier: Programming Language :: Python :: 3
Classifier: Programming Language :: Python :: 3.8
Classifier: Programming Language :: Python :: 3.9
Classifier: Programming Language :: Python :: 3.10
Classifier: Programming Language :: Python :: 3.11
Classifier: Programming Language :: Python :: 3.12
Requires-Dist: nonebot2 (>=2.2.0,<3.0.0)
Project-URL: Documentation, https://github.com/he0119/nonebot-plugin-treehelp#readme
Project-URL: Repository, https://github.com/he0119/nonebot-plugin-treehelp
